perceptra_zero_shot/__init__.py
perceptra_zero_shot/__version__.py
perceptra_zero_shot/api/__init__.py
perceptra_zero_shot/api/main.py
perceptra_zero_shot/api/models.py
perceptra_zero_shot/api/routes.py
perceptra_zero_shot/cli/__init__.py
perceptra_zero_shot/cli/main.py
perceptra_zero_shot/core/__init__.py
perceptra_zero_shot/core/detector.py
perceptra_zero_shot/core/result.py
perceptra_zero_shot/models/__init__.py
perceptra_zero_shot/models/base.py
perceptra_zero_shot/models/grounding_dino.py
perceptra_zero_shot/models/owlv2.py
perceptra_zero_shot/models/registry.py
perceptra_zero_shot/utils/__init__.py
perceptra_zero_shot/utils/image.py
perceptra_zero_shot/utils/visualization.py
perceptra_zero_shot-0.1.0.dist-info/licenses/LICENSE
perceptra_zero_shot-0.1.0.dist-info/METADATA
perceptra_zero_shot-0.1.0.dist-info/WHEEL
perceptra_zero_shot-0.1.0.dist-info/entry_points.txt
perceptra_zero_shot-0.1.0.dist-info/top_level.txt
perceptra_zero_shot-0.1.0.dist-info/RECORD
