Metadata-Version: 2.4
Name: perceptra-zero-shot
Version: 0.1.0
Summary: Production-ready zero-shot object detection and segmentation toolkit
Author-email: Tannous Geagea <tannousgeagea@hotmail.com>
License: MIT
Project-URL: Homepage, https://github.com/tannousgeagea/perceptra-zero-shot
Project-URL: Documentation, https://perceptra-zero-shot.readthedocs.io
Project-URL: Repository, https://github.com/tannousgeagea/perceptra-zero-shot
Project-URL: Issues, https://github.com/tannousgeagea/perceptra-zero-shot/issues
Keywords: computer-vision,object-detection,zero-shot,deep-learning,vision-language-models
Classifier: Development Status :: 4 - Beta
Classifier: Intended Audience :: Developers
Classifier: Intended Audience :: Science/Research
Classifier: License :: OSI Approved :: MIT License
Classifier: Programming Language :: Python :: 3
Classifier: Programming Language :: Python :: 3.8
Classifier: Programming Language :: Python :: 3.9
Classifier: Programming Language :: Python :: 3.10
Classifier: Programming Language :: Python :: 3.11
Classifier: Programming Language :: Python :: 3.12
Classifier: Topic :: Scientific/Engineering :: Artificial Intelligence
Classifier: Topic :: Scientific/Engineering :: Image Recognition
Requires-Python: >=3.8
License-File: LICENSE
Requires-Dist: torch>=2.0.0
Requires-Dist: torchvision>=0.15.0
Requires-Dist: transformers>=4.30.0
Requires-Dist: pillow>=9.0.0
Requires-Dist: numpy<2.0.0,>=1.21.0
Requires-Dist: opencv-python>=4.5.0
Requires-Dist: scipy>=1.7.0
Requires-Dist: timm>=0.9.0
Requires-Dist: huggingface-hub>=0.14.0
Provides-Extra: dev
Requires-Dist: pytest>=7.0.0; extra == "dev"
Requires-Dist: pytest-cov>=4.0.0; extra == "dev"
Requires-Dist: pytest-asyncio>=0.21.0; extra == "dev"
Requires-Dist: black>=22.0.0; extra == "dev"
Requires-Dist: flake8>=4.0.0; extra == "dev"
Requires-Dist: mypy>=0.950; extra == "dev"
Requires-Dist: isort>=5.10.0; extra == "dev"
Provides-Extra: api
Requires-Dist: fastapi>=0.104.0; extra == "api"
Requires-Dist: uvicorn[standard]>=0.24.0; extra == "api"
Requires-Dist: python-multipart>=0.0.6; extra == "api"
Requires-Dist: pydantic>=2.0.0; extra == "api"
Requires-Dist: pydantic-settings>=2.0.0; extra == "api"
Provides-Extra: cli
Requires-Dist: click>=8.0.0; extra == "cli"
Requires-Dist: rich>=13.0.0; extra == "cli"
Requires-Dist: tqdm>=4.65.0; extra == "cli"
Provides-Extra: viz
Requires-Dist: matplotlib>=3.5.0; extra == "viz"
Provides-Extra: all
Requires-Dist: perceptra-zero-shot[api,cli,dev,viz]; extra == "all"
Dynamic: license-file
